<annotation>
	<folder>personnel</folder>
	<filename>000133.jpg</filename>
	<path>/home/wy/YOLOv3_SaveVideo-master/darknet/data/personnel/000133.jpg</path>
	<source>
		<database>Unknown</database>
	</source>
	<size>
		<width>375</width>
		<height>500</height>
		<depth>3</depth>
	</size>
	<segmented>0</segmented>
	<object>
		<name>noworker</name>
		<pose>Unspecified</pose>
		<truncated>1</truncated>
		<difficult>0</difficult>
		<bndbox>
			<xmin>108</xmin>
			<ymin>182</ymin>
			<xmax>375</xmax>
			<ymax>388</ymax>
		</bndbox>
	</object>
</annotation>
